semantics/__init__.py
semantics/number.py
semantics/solver.py
semantics/unit.py
Ekpenisi-0.1.0.dist-info/METADATA
Ekpenisi-0.1.0.dist-info/WHEEL
Ekpenisi-0.1.0.dist-info/top_level.txt
Ekpenisi-0.1.0.dist-info/RECORD
